{"is_source_file": true, "format": "JavaScript (React JSX)", "description": "This file defines a React component 'StartKYC' that manages the user onboarding process, including rendering onboarding forms, document upload, and KYC status components based on user interaction.", "external_files": ["../components/KYC/OnboardingForm", "../components/KYC/DocumentUpload", "../components/KYC/KycStatus"], "external_methods": ["React, { useState } from 'react'", "OnboardingForm onStarted", "DocumentUpload caseId", "KycStatus caseId"], "published": ["default export StartKYC"], "classes": [], "methods": [{"name": "StartKYC()", "description": "React functional component that manages the state for onboarding case information and conditionally renders onboarding, document upload, and status components.", "scope": "", "scopeKind": ""}], "calls": ["useState", "OnboardingForm", "DocumentUpload", "KycStatus"], "search-terms": ["React component", "KYC onboarding", "start KYC process", "document upload", "React hooks"], "state": 2, "file_id": 23, "knowledge_revision": 53, "git_revision": "", "ctags": [{"_type": "tag", "name": "StartKYC", "path": "/home/kavia/workspace/code-generation/ekyc-41822-41866/WebFrontend/src/pages/StartKYC.js", "pattern": "/^export default function StartKYC() {$/", "language": "JavaScript", "kind": "function", "signature": "()"}, {"_type": "tag", "name": "setCaseInfo", "path": "/home/kavia/workspace/code-generation/ekyc-41822-41866/WebFrontend/src/pages/StartKYC.js", "pattern": "/^      {!caseInfo && <OnboardingForm onStarted={setCaseInfo} \\/>}$/", "language": "JavaScript", "kind": "field", "scope": "StartKYC.AnonymousClass7e2f21ca0101", "scopeKind": "class"}], "hash": "4ab006f917ffe0347a7b6ac2f4f65fc4", "format-version": 4, "code-base-name": "WebFrontend", "filename": "WebFrontend/src/pages/StartKYC.js", "fields": [{"name": "{!caseInfo && <OnboardingForm onStarted={setCaseInfo} \\/>}", "scope": "StartKYC.AnonymousClass7e2f21ca0101", "scopeKind": "class", "description": "unavailable"}], "revision_history": [{"53": ""}]}